syriskmodels/__init__.py
syriskmodels/detector.py
syriskmodels/evaluate.py
syriskmodels/logging.py
syriskmodels/models.py
syriskmodels/rule.py
syriskmodels/scorecard.py
syriskmodels/utils.py
syriskmodels/contrib/__init__.py
syriskmodels/contrib/build_scorecard.py
syriskmodels/contrib/var_select.py
syriskmodels-0.2.6.dist-info/LICENSE
syriskmodels-0.2.6.dist-info/METADATA
syriskmodels-0.2.6.dist-info/WHEEL
syriskmodels-0.2.6.dist-info/top_level.txt
syriskmodels-0.2.6.dist-info/RECORD
