Metadata-Version: 2.1
Name: syriskmodels
Version: 0.2.6
Summary: 信用风险模型工具包
Author-email: YAO Siyuan <siyuan89@163.com>
Project-URL: Homepage, https://github.com/siyuany/riskmodels
Project-URL: Bug Tracker, https://github.com/siyuany/riskmodels/issues
Classifier: Programming Language :: Python :: 3
Classifier: License :: OSI Approved :: MIT License
Classifier: Operating System :: OS Independent
Requires-Python: >=3.6
License-File: LICENSE
Requires-Dist: pandas ==1.*,>=1.5
Requires-Dist: matplotlib >=3.3
Requires-Dist: numpy >=1.26.0
Requires-Dist: scipy >=1.6
Requires-Dist: scikit-learn >=1.4.0
Requires-Dist: statsmodels >=0.14.0
Requires-Dist: numba ==0.60.*
